README.md
setup.py
littleballoffur/__init__.py
littleballoffur/backend.py
littleballoffur/helpers.py
littleballoffur/sampler.py
littleballoffur/version.py
littleballoffur.egg-info/PKG-INFO
littleballoffur.egg-info/SOURCES.txt
littleballoffur.egg-info/dependency_links.txt
littleballoffur.egg-info/requires.txt
littleballoffur.egg-info/top_level.txt
littleballoffur/dataset/__init__.py
littleballoffur/dataset/dataset_reader.py
littleballoffur/edge_sampling/__init__.py
littleballoffur/edge_sampling/hybridnodeedgesampler.py
littleballoffur/edge_sampling/randomedgesampler.py
littleballoffur/edge_sampling/randomedgesamplerwithinduction.py
littleballoffur/edge_sampling/randomedgesamplerwithpartialinduction.py
littleballoffur/edge_sampling/randomnodeedgesampler.py
littleballoffur/exploration_sampling/__init__.py
littleballoffur/exploration_sampling/breadthfirstsearchsampler.py
littleballoffur/exploration_sampling/circulatedneighborsrandomwalksampler.py
littleballoffur/exploration_sampling/commonneighborawarerandomwalksampler.py
littleballoffur/exploration_sampling/communitystructureexpansionsampler.py
littleballoffur/exploration_sampling/depthfirstsearchsampler.py
littleballoffur/exploration_sampling/diffusionsampler.py
littleballoffur/exploration_sampling/diffusiontreesampler.py
littleballoffur/exploration_sampling/forestfiresampler.py
littleballoffur/exploration_sampling/frontiersampler.py
littleballoffur/exploration_sampling/looperasedrandomwalksampler.py
littleballoffur/exploration_sampling/metropolishastingsrandomwalksampler.py
littleballoffur/exploration_sampling/nonbacktrackingrandomwalksampler.py
littleballoffur/exploration_sampling/randomnodeneighborsampler.py
littleballoffur/exploration_sampling/randomwalksampler.py
littleballoffur/exploration_sampling/randomwalkwithjumpsampler.py
littleballoffur/exploration_sampling/randomwalkwithrestartsampler.py
littleballoffur/exploration_sampling/shortestpathsampler.py
littleballoffur/exploration_sampling/snowballsampler.py
littleballoffur/exploration_sampling/spikyballsampler.py
littleballoffur/node_sampling/__init__.py
littleballoffur/node_sampling/degreebasedsampler.py
